pic_chrono/__init__.py
pic_chrono/__main__.py
pic_chrono/renamer.py
pic_chrono-1.0.0.dist-info/LICENSE
pic_chrono-1.0.0.dist-info/METADATA
pic_chrono-1.0.0.dist-info/WHEEL
pic_chrono-1.0.0.dist-info/entry_points.txt
pic_chrono-1.0.0.dist-info/RECORD
