Metadata-Version: 2.1
Name: pic-chrono
Version: 1.0.0
Summary: A tool to automaticallly rename images to their respective date-time taken
Home-page: https://github.com/kondakoffer/PicChrono
License: MIT
Keywords: Metadata extraction,Date-time extraction,File renaming,Pillow library,Media organization
Author: Valentin Ruben Kondakov
Author-email: kondakov.valentin@icloud.com
Requires-Python: >=3.10,<4.0
Classifier: License :: OSI Approved :: MIT License
Classifier: Programming Language :: Python :: 3
Classifier: Programming Language :: Python :: 3.10
Classifier: Programming Language :: Python :: 3.11
Requires-Dist: Pillow (>=9.3)
Requires-Dist: rich (>=13.4.1,<14.0.0)
Requires-Dist: typer (>=0.9.0,<0.10.0)
Project-URL: Documentation, https://github.com/kondakoffer/PicChrono
Project-URL: Repository, https://github.com/kondakoffer/PicChrono
